bee_rpc/__init__.py
bee_rpc/balancer.py
bee_rpc/channel.py
bee_rpc/client.py
bee_rpc/codec.py
bee_rpc/node.py
bee_rpc/server.py
bee_rpc/transport.py
bee_rpc/codecs/__init__.py
bee_rpc/codecs/http/__init__.py
bee_rpc/codecs/json/__init__.py
bee_rpc/codecs/json/json.py
bee_rpc/codecs/proto/__init__.py
bee_rpc/codecs/proto/msg_pb2.py
bee_rpc/codecs/proto/msg_test.py
bee_rpc/codecs/proto/proto.py
bee_rpc/registry/__init__.py
bee_rpc/registry/builder.py
bee_rpc/registry/consul_registry.py
bee_rpc/registry/consul_test.py
bee_rpc/registry/direct_registry.py
bee_rpc/registry/etcd3_test.py
bee_rpc/registry/etcdv3_registry.py
bee_rpc/registry/registry.py
py_bee_rpc-0.1.1.dist-info/LICENSE.rst
py_bee_rpc-0.1.1.dist-info/METADATA
py_bee_rpc-0.1.1.dist-info/WHEEL
py_bee_rpc-0.1.1.dist-info/top_level.txt
py_bee_rpc-0.1.1.dist-info/RECORD
