Metadata-Version: 2.1
Name: py-bee-rpc
Version: 0.1.1
Summary: Bee is an all-in-one python framework for simplifying micro service program development.
Home-page: https://github.com/py-bee/bee-rpc
Author: wenchao.hao
Author-email: awenhaowenchao@hotmail.com
License: MIT
Platform: UNKNOWN
Classifier: License :: OSI Approved :: MIT License
Classifier: Programming Language :: Python
Classifier: Programming Language :: Python :: 3
Classifier: Programming Language :: Python :: 3.6
Classifier: Programming Language :: Python :: Implementation :: CPython
Classifier: Programming Language :: Python :: Implementation :: PyPy
Requires-Python: >=3.6.0
License-File: LICENSE.rst
Requires-Dist: gevent (==1.4.0)
Requires-Dist: greenlet (==1.0.0)
Requires-Dist: py-bee-config (>=0.1.0)
Requires-Dist: py-bee-util (>=0.1.1)
Requires-Dist: etcd3 (==0.12.0)
Requires-Dist: py-consul (==1.2.2)
Requires-Dist: google (==3.0.0)
Requires-Dist: protobuf (==3.15.6)
Requires-Dist: grpcio (==1.36.1)
Requires-Dist: gsocketpool (==0.1.6)
